AUTHORS.rst
HISTORY.rst
LICENSE
MANIFEST.in
README.md
setup.cfg
setup.py
simply/__init__.py
simply/platform.py
simply/utils.py
simply.egg-info/PKG-INFO
simply.egg-info/SOURCES.txt
simply.egg-info/dependency_links.txt
simply.egg-info/not-zip-safe
simply.egg-info/requires.txt
simply.egg-info/top_level.txt
simply/backends/__init__.py
simply/backends/docker.py
simply/frontends/__init__.py
simply/frontends/busybox.py
simply/frontends/debian.py
simply/frontends/linux.py
simply/images/conda2/Dockerfile
simply/images/conda2/conda_install.sh
simply/images/conda3/Dockerfile
simply/images/conda3/conda_install.sh
simply/images/debian8/Dockerfile
simply/images/phusion/Dockerfile
simply/images/scratch/Dockerfile
tests/__init__.py
tests/conftest.py
tests/requirements.txt
tests/test_docker.py
tests/test_images.py
tests/test_platform.py
tests/test_utils.py
tests/.cache/v/cache/lastfailed